ENT3C/__init__.py
ENT3C/__version__.py
ENT3C/cli/__init__.py
ENT3C/cli/main.py
ENT3C/core/__init__.py
ENT3C/core/get_entropy_table.py
ENT3C/core/get_similarity_table.py
ENT3C/core/locate_difference.py
ENT3C/core/utils.py
ENT3C/core/vN_entropy.py
ent3c-2.2.2.dist-info/licenses/LICENSE
ent3c-2.2.2.dist-info/METADATA
ent3c-2.2.2.dist-info/WHEEL
ent3c-2.2.2.dist-info/entry_points.txt
ent3c-2.2.2.dist-info/top_level.txt
ent3c-2.2.2.dist-info/RECORD
