Metadata-Version: 2.4
Name: ENT3C
Version: 2.2.2
Summary: Compute similarity between genomic contact matrices with "Entropy 3C" 
Author-email: Xenia Lainscsek <108679125+X3N1A@users.noreply.github.com>
License-Expression: GPL-3.0-or-later
Project-URL: Repository, https://github.com/X3N1A/ENT3C
Keywords: Hi-C,micro-C,similarity,entropy
Requires-Python: >=3.11
License-File: LICENSE
Requires-Dist: cooler>=0.9.0
Requires-Dist: matplotlib>=3.6.0
Requires-Dist: numpy>=2.0.0
Requires-Dist: pandas>=2.3.0
Dynamic: license-file
